tailpyscss/__init__.py
tailpyscss/builder.py
tailpyscss/generator.py
tailpyscss/scanner.py
tailpyscss/vibes.py
tailpyscss/cli/__init__.py
tailpyscss/cli/__main__.py
tailpyscss/cli/main.py
tailpyscss/cli/commands/__init__.py
tailpyscss/cli/commands/build.py
tailpyscss/cli/commands/init.py
tailpyscss/cli/commands/setup.py
tailpyscss/cli/commands/watch.py
tailpyscss/cli/core/__init__.py
tailpyscss/cli/core/bridge.py
tailpyscss/cli/core/cache.py
tailpyscss/cli/core/config.py
tailpyscss/cli/core/security.py
tailpyscss/generators/__init__.py
tailpyscss/generators/base.py
tailpyscss/generators/borders.py
tailpyscss/generators/colors.py
tailpyscss/generators/effects.py
tailpyscss/generators/layout.py
tailpyscss/generators/spacing.py
tailpyscss/generators/typography.py
tailpyscss/ui/__init__.py
tailpyscss/ui/core.py
tailpyscss/ui/shortcuts.py
tailpyscss-0.5.3.dist-info/licenses/LICENSE
tailpyscss-0.5.3.dist-info/METADATA
tailpyscss-0.5.3.dist-info/WHEEL
tailpyscss-0.5.3.dist-info/entry_points.txt
tailpyscss-0.5.3.dist-info/top_level.txt
tailpyscss-0.5.3.dist-info/RECORD
