Metadata-Version: 2.4
Name: tailpyscss
Version: 0.5.3
Summary: A Python-native utility-first CSS generator and compiler.
Home-page: https://github.com/tailpyscss2/tailpyscss-framework
Author: Abdi Abdikarim
Project-URL: Source, https://github.com/tailpyscss2/tailpyscss-framework
Keywords: css,scss,tailwind,utility,design system,python css,jinja css,no node css,python tailwind alternative,style framework,ui framework,python styling framework
Classifier: Programming Language :: Python :: 3
Classifier: License :: OSI Approved :: MIT License
Classifier: Operating System :: OS Independent
Classifier: Framework :: Flask
Classifier: Framework :: Django
Classifier: Topic :: Software Development :: User Interfaces
Classifier: Topic :: Internet :: WWW/HTTP :: Dynamic Content
Requires-Python: >=3.8
License-File: LICENSE
Requires-Dist: libsass>=0.22.0
Requires-Dist: watchdog>=2.1.0
Dynamic: author
Dynamic: classifier
Dynamic: description
Dynamic: description-content-type
Dynamic: home-page
Dynamic: keywords
Dynamic: license-file
Dynamic: project-url
Dynamic: requires-dist
Dynamic: requires-python
Dynamic: summary
